flaredantic/__init__.py
flaredantic/__version__.py
flaredantic/cli.py
flaredantic/tunnel_manager.py
flaredantic/base/__init__.py
flaredantic/base/config.py
flaredantic/base/downloader.py
flaredantic/base/tunnel.py
flaredantic/core/__init__.py
flaredantic/core/exceptions.py
flaredantic/core/logging_config.py
flaredantic/core/notify.py
flaredantic/tunnel/__init__.py
flaredantic/tunnel/cloudflare/__init__.py
flaredantic/tunnel/cloudflare/config.py
flaredantic/tunnel/cloudflare/downloader.py
flaredantic/tunnel/cloudflare/tunnel.py
flaredantic/tunnel/microsoft/__init__.py
flaredantic/tunnel/microsoft/config.py
flaredantic/tunnel/microsoft/downloader.py
flaredantic/tunnel/microsoft/tunnel.py
flaredantic/tunnel/serveo/__init__.py
flaredantic/tunnel/serveo/config.py
flaredantic/tunnel/serveo/downloader.py
flaredantic/tunnel/serveo/tunnel.py
flaredantic/utils/__init__.py
flaredantic/utils/serveo.py
flaredantic/utils/ssh.py
flaredantic/utils/termux.py
flaredantic-0.1.5.dist-info/licenses/LICENSE
flaredantic-0.1.5.dist-info/METADATA
flaredantic-0.1.5.dist-info/WHEEL
flaredantic-0.1.5.dist-info/entry_points.txt
flaredantic-0.1.5.dist-info/top_level.txt
flaredantic-0.1.5.dist-info/RECORD
