Metadata-Version: 2.4
Name: flaredantic
Version: 0.1.5
Summary: Create Cloudflare, Microsoft, and Serveo tunnels with ease.
Author-email: linuztx <linuztx@gmail.com>
License-Expression: Apache-2.0
Project-URL: Homepage, https://github.com/linuztx/flaredantic
Project-URL: Repository, https://github.com/linuztx/flaredantic
Project-URL: Issues, https://github.com/linuztx/flaredantic/issues
Keywords: cloudflare,serveo,microsoft,tunnel,networking,proxy,localhost,expose,ngrok-alternative
Classifier: Development Status :: 4 - Beta
Classifier: Environment :: Console
Classifier: Operating System :: OS Independent
Classifier: Intended Audience :: Information Technology
Classifier: Intended Audience :: System Administrators
Classifier: Intended Audience :: Developers
Classifier: Topic :: Internet
Classifier: Topic :: System :: Networking
Classifier: Topic :: Software Development :: Libraries :: Python Modules
Classifier: Programming Language :: Python :: 3
Classifier: Programming Language :: Python :: 3 :: Only
Classifier: Programming Language :: Python :: 3.6
Classifier: Programming Language :: Python :: 3.7
Classifier: Programming Language :: Python :: 3.8
Classifier: Programming Language :: Python :: 3.9
Classifier: Programming Language :: Python :: 3.10
Classifier: Programming Language :: Python :: 3.11
Classifier: Programming Language :: Python :: 3.12
Classifier: Programming Language :: Python :: 3.13
Requires-Python: >=3.6
License-File: LICENSE
Requires-Dist: requests
Requires-Dist: tqdm
Dynamic: license-file
